rfive-0.2.dist-info/DESCRIPTION.rst
rfive-0.2.dist-info/top_level.txt
rfive-0.2.dist-info/METADATA
rfive-0.2.dist-info/metadata.json
rfive-0.2.dist-info/WHEEL
rfive-0.2.dist-info/RECORD
rfive/version.py
rfive/__init__.py
rfive/fabricSSH.py
