Metadata-Version: 2.0
Name: rfive
Version: 0.2
Summary: A unified interface into multiple cloud providers.
Home-page: https://github.com/iPlantCollaborativeOpenSource/rfive
Author: iPlant Collaborative
Author-email: atmodevs@gmail.com
License: Apache License, Version 2.0
Platform: UNKNOWN
Classifier: Development Status :: 4 - Beta
Classifier: Intended Audience :: Developers
Classifier: Intended Audience :: Information Technology
Classifier: License :: OSI Approved :: Apache Software License
Classifier: Operating System :: OS Independent
Classifier: Programming Language :: Python
Classifier: Topic :: Software Development :: Libraries
Classifier: Topic :: System
Classifier: Topic :: System :: Clustering
Classifier: Topic :: System :: Distributed Computing
Classifier: Topic :: System :: Systems Administration
Requires-Dist: Fabric (==1.10)
